bw2_annotation_utils/cache_utils.py
bw2_annotation_utils/get_MANE_table.py
bw2_annotation_utils/get_clingen_table.py
bw2_annotation_utils/get_ensembl_db_info.py
bw2_annotation_utils/get_hgnc_table.py
bw2_annotation_utils/get_omim_table.py
bw2_annotation_utils/get_panel_app_table.py
bw2_annotation_utils/gtf_utils.py
bw2_annotation_utils/hpo_lookup.py
bw2_annotation_utils-0.1.4.dist-info/METADATA
bw2_annotation_utils-0.1.4.dist-info/WHEEL
bw2_annotation_utils-0.1.4.dist-info/entry_points.txt
bw2_annotation_utils-0.1.4.dist-info/top_level.txt
bw2_annotation_utils-0.1.4.dist-info/RECORD
