Metadata-Version: 2.1
Name: bw2-annotation-utils
Version: 0.1.4
Summary: Misc. utilities for downloading and working with various gene annotations, the HPO ontology, etc
Home-page: https://github.com/bw2/annotation-utils
License: MIT
Classifier: Development Status :: 4 - Beta
Classifier: Intended Audience :: Developers
Classifier: License :: OSI Approved :: MIT License
Classifier: Natural Language :: English
Classifier: Programming Language :: Python :: 3
Classifier: Programming Language :: Python :: 3.7
Classifier: Programming Language :: Python :: 3.8
Classifier: Programming Language :: Python :: 3.9
Classifier: Programming Language :: Python :: Implementation :: CPython
Classifier: Programming Language :: Python :: Implementation :: PyPy
Requires-Python: >=3.7
Requires-Dist: pandas (>=1.3.5)
Requires-Dist: pymysql (>=1.1.0)
